pyhud/__init__.py
hudata-0.0.0a0.dist-info/METADATA
hudata-0.0.0a0.dist-info/WHEEL
hudata-0.0.0a0.dist-info/top_level.txt
hudata-0.0.0a0.dist-info/RECORD
